broadcast_server/__init__.py
broadcast_server/cli.py
broadcast_server/client.py
broadcast_server/server.py
broadcast_server-0.1.dist-info/METADATA
broadcast_server-0.1.dist-info/WHEEL
broadcast_server-0.1.dist-info/entry_points.txt
broadcast_server-0.1.dist-info/top_level.txt
broadcast_server-0.1.dist-info/RECORD
